ez_logger/__init__.py
ez_logger/base_logger.py
ez_logger/console_logger.py
ez_logger/default_logger.py
ez_logger/file_logger.py
ez_logger/tenant_logger.py
ez_logger-1.1.10.dist-info/METADATA
ez_logger-1.1.10.dist-info/WHEEL
ez_logger-1.1.10.dist-info/top_level.txt
ez_logger-1.1.10.dist-info/RECORD
