Metadata-Version: 2.1
Name: ez-logger
Version: 1.1.10
Summary: ez-logger allows you to a logger for everyday operations
Home-page: https://github.com/varmarakesh/ez-logger
Author: Rakesh V
Author-email: varma.rakesh@gmail.com
License: BSD
Platform: UNKNOWN
Classifier: Development Status :: 5 - Production/Stable
Classifier: Intended Audience :: Developers
Classifier: Operating System :: MacOS :: MacOS X
Classifier: Operating System :: Microsoft :: Windows
Classifier: Operating System :: POSIX :: Linux
Classifier: Programming Language :: Python :: 2.7
Classifier: Programming Language :: Python :: 3.6
Classifier: Programming Language :: Python :: Implementation :: CPython
Requires-Dist: colorlog (==4.0.2)
